accuweather/__init__.py
accuweather/accuApi.py
accuweather/apiconfig.py
accuweather/url.py
accuweather/objects/__init__.py
accuweather/objects/accuweatherFactory.py
accuweather/objects/accuweather_factory.py
accuweather/objects/currentConditions.py
accuwython-0.2.1.dist-info/DESCRIPTION.rst
accuwython-0.2.1.dist-info/METADATA
accuwython-0.2.1.dist-info/RECORD
accuwython-0.2.1.dist-info/WHEEL
accuwython-0.2.1.dist-info/metadata.json
accuwython-0.2.1.dist-info/top_level.txt
