Metadata-Version: 2.0
Name: accuwython
Version: 0.2.1
Summary: This Wrapper for AccuWeather API
Home-page: https://juanpa_findasense@bitbucket.org/juanpa_findasense/accuweather.git
Author: Findasense Intelligence
Author-email: juanpablo@findasense.com
License: MIT
Keywords: accuweather weather
Platform: UNKNOWN
Classifier: Development Status :: 3 - Alpha
Classifier: Intended Audience :: Developers
Classifier: Topic :: Software Development :: Build Tools
Classifier: License :: OSI Approved :: MIT License
Classifier: Programming Language :: Python :: 2
Classifier: Programming Language :: Python :: 2.6
Classifier: Programming Language :: Python :: 2.7
